{
  "annotations": {
    "list": []
  },
  "editable": true,
  "fiscalYearStartMonth": 0,
  "graphTooltip": 0,
  "id": null,
  "links": [],
  "liveNow": true,
  "panels": [
    {
      "datasource": {
        "type": "loki",
        "uid": "loki"
      },
      "gridPos": {
        "h": 12,
        "w": 24,
        "x": 0,
        "y": 0
      },
      "id": 1,
      "options": {
        "dedupStrategy": "none",
        "enableLogDetails": true,
        "prettifyLogMessage": false,
        "showCommonLabels": false,
        "showLabels": false,
        "showTime": true,
        "sortOrder": "Descending",
        "wrapLogMessage": false
      },
      "pluginVersion": "10.2.0",
      "targets": [
        {
          "datasource": {
            "type": "loki",
            "uid": "loki"
          },
          "expr": "{job=\"price_bot\"}",
          "refId": "A"
        }
      ],
      "title": "Live Activity Logs",
      "type": "logs"
    },
    {
      "datasource": {
        "type": "prometheus",
        "uid": "prometheus"
      },
      "fieldConfig": {
        "defaults": {
          "color": {
            "mode": "palette-classic"
          },
          "custom": {
            "axisBorderShow": false,
            "axisCenteredZero": false,
            "axisColorMode": "text",
            "axisLabel": "",
            "axisPlacement": "auto",
            "barAlignment": 0,
            "drawStyle": "line",
            "fillOpacity": 10,
            "gradientMode": "none",
            "hideFrom": {
              "legend": false,
              "tooltip": false,
              "viz": false
            },
            "insertNulls": false,
            "lineInterpolation": "smooth",
            "lineWidth": 2,
            "pointSize": 5,
            "scaleDistribution": {
              "type": "linear"
            },
            "showPoints": "never",
            "spanNulls": false,
            "stacking": {
              "group": "A",
              "mode": "none"
            },
            "thresholdsStyle": {
              "mode": "off"
            }
          },
          "mappings": [],
          "thresholds": {
            "mode": "absolute",
            "steps": [
              {
                "color": "green",
                "value": null
              }
            ]
          },
          "unit": "reqps"
        },
        "overrides": []
      },
      "gridPos": {
        "h": 8,
        "w": 12,
        "x": 0,
        "y": 12
      },
      "id": 2,
      "options": {
        "legend": {
          "calcs": [
            "mean",
            "max"
          ],
          "displayMode": "table",
          "placement": "right",
          "showLegend": true
        },
        "tooltip": {
          "mode": "multi",
          "sort": "none"
        }
      },
      "pluginVersion": "10.2.0",
      "targets": [
        {
          "datasource": {
            "type": "prometheus",
            "uid": "prometheus"
          },
          "expr": "rate(price_fetches_total[1m])",
          "legendFormat": "{{store}} - {{status}}",
          "refId": "A"
        }
      ],
      "title": "Fetch Activity (per second)",
      "type": "timeseries"
    },
    {
      "datasource": {
        "type": "prometheus",
        "uid": "prometheus"
      },
      "fieldConfig": {
        "defaults": {
          "color": {
            "mode": "palette-classic"
          },
          "custom": {
            "axisBorderShow": false,
            "axisCenteredZero": false,
            "axisColorMode": "text",
            "axisLabel": "",
            "axisPlacement": "auto",
            "barAlignment": 0,
            "drawStyle": "line",
            "fillOpacity": 10,
            "gradientMode": "none",
            "hideFrom": {
              "legend": false,
              "tooltip": false,
              "viz": false
            },
            "insertNulls": false,
            "lineInterpolation": "smooth",
            "lineWidth": 2,
            "pointSize": 5,
            "scaleDistribution": {
              "type": "linear"
            },
            "showPoints": "never",
            "spanNulls": false,
            "stacking": {
              "group": "A",
              "mode": "none"
            },
            "thresholdsStyle": {
              "mode": "off"
            }
          },
          "mappings": [],
          "thresholds": {
            "mode": "absolute",
            "steps": [
              {
                "color": "green",
                "value": null
              }
            ]
          },
          "unit": "s"
        },
        "overrides": []
      },
      "gridPos": {
        "h": 8,
        "w": 12,
        "x": 12,
        "y": 12
      },
      "id": 3,
      "options": {
        "legend": {
          "calcs": [
            "mean",
            "max"
          ],
          "displayMode": "table",
          "placement": "right",
          "showLegend": true
        },
        "tooltip": {
          "mode": "multi",
          "sort": "none"
        }
      },
      "pluginVersion": "10.2.0",
      "targets": [
        {
          "datasource": {
            "type": "prometheus",
            "uid": "prometheus"
          },
          "expr": "histogram_quantile(0.50, sum(rate(price_fetch_duration_seconds_bucket[5m])) by (le, store))",
          "legendFormat": "{{store}} p50",
          "refId": "A"
        },
        {
          "datasource": {
            "type": "prometheus",
            "uid": "prometheus"
          },
          "expr": "histogram_quantile(0.95, sum(rate(price_fetch_duration_seconds_bucket[5m])) by (le, store))",
          "legendFormat": "{{store}} p95",
          "refId": "B"
        },
        {
          "datasource": {
            "type": "prometheus",
            "uid": "prometheus"
          },
          "expr": "histogram_quantile(0.99, sum(rate(price_fetch_duration_seconds_bucket[5m])) by (le, store))",
          "legendFormat": "{{store}} p99",
          "refId": "C"
        }
      ],
      "title": "Fetch Latency Distribution",
      "type": "timeseries"
    },
    {
      "datasource": {
        "type": "loki",
        "uid": "loki"
      },
      "gridPos": {
        "h": 8,
        "w": 24,
        "x": 0,
        "y": 20
      },
      "id": 4,
      "options": {
        "dedupStrategy": "none",
        "enableLogDetails": true,
        "prettifyLogMessage": false,
        "showCommonLabels": false,
        "showLabels": false,
        "showTime": true,
        "sortOrder": "Descending",
        "wrapLogMessage": false
      },
      "pluginVersion": "10.2.0",
      "targets": [
        {
          "datasource": {
            "type": "loki",
            "uid": "loki"
          },
          "expr": "{job=\"price_bot\"} |= \"ERROR\"",
          "refId": "A"
        }
      ],
      "title": "Error Logs",
      "type": "logs"
    }
  ],
  "refresh": "10s",
  "schemaVersion": 38,
  "tags": [
    "price-error-bot"
  ],
  "templating": {
    "list": []
  },
  "time": {
    "from": "now-1h",
    "to": "now"
  },
  "timepicker": {},
  "timezone": "",
  "title": "Price Error Bot - Live Activity",
  "uid": "price-bot-activity",
  "version": 1,
  "weekStart": ""
}
